orvion/__init__.py
orvion/cache.py
orvion/client.py
orvion/exceptions.py
orvion/matcher.py
orvion/models.py
orvion/telemetry.py
orvion/x402.py
orvion/fastapi/__init__.py
orvion/fastapi/decorators.py
orvion/fastapi/middleware.py
orvion/fastapi/routers.py
orvion/testing/__init__.py
orvion/testing/mocks.py
orvion-0.5.3.dist-info/METADATA
orvion-0.5.3.dist-info/WHEEL
orvion-0.5.3.dist-info/top_level.txt
orvion-0.5.3.dist-info/RECORD
